lawu/__init__.py
lawu/_instruction.py
lawu/ast.py
lawu/attribute.py
lawu/blocks.py
lawu/cf.py
lawu/classloader.py
lawu/constants.py
lawu/fields.py
lawu/instructions.py
lawu/methods.py
lawu/attributes/__init__.py
lawu/attributes/code.py
lawu/cli/__init__.py
lawu/cli/bytecode.py
lawu/cli/debug.py
lawu/util/__init__.py
lawu/util/bytecode.py
lawu/util/descriptor.py
lawu/util/flags.py
lawu/util/shell.py
lawu/util/stream.py
lawu/util/tracer.py
lawu/util/utf.py
lawu/util/verifier.py
lawu-3.0.0.dist-info/LICENCE
lawu-3.0.0.dist-info/METADATA
lawu-3.0.0.dist-info/WHEEL
lawu-3.0.0.dist-info/entry_points.txt
lawu-3.0.0.dist-info/top_level.txt
lawu-3.0.0.dist-info/RECORD
