Metadata-Version: 2.1
Name: lawu
Version: 3.0.0
Summary: Doing fun stuff with JVM ClassFiles.
Home-page: http://github.com/TkTech/lawu
Author: Tyler Kennedy
Author-email: tk@tkte.ch
License: UNKNOWN
Keywords: java,disassembly,disassembler,assembly
Platform: UNKNOWN
Classifier: Programming Language :: Python
Classifier: License :: OSI Approved :: MIT License
Classifier: Operating System :: OS Independent
Classifier: Development Status :: 3 - Alpha
Classifier: Intended Audience :: Developers
Classifier: Topic :: Software Development :: Disassemblers
Requires-Dist: click (>=7.0)
Provides-Extra: dev
Requires-Dist: pytest ; extra == 'dev'
Requires-Dist: sphinx ; extra == 'dev'
Requires-Dist: sphinxcontrib-googleanalytics ; extra == 'dev'
Requires-Dist: sphinx-rtd-theme ; extra == 'dev'
Requires-Dist: sphinx-click ; extra == 'dev'
Requires-Dist: ghp-import ; extra == 'dev'
Requires-Dist: pyyaml ; extra == 'dev'
Requires-Dist: twine ; extra == 'dev'
Requires-Dist: wheel ; extra == 'dev'
